{
  "builds": [
    {
      "name": "rhel8",
      "builder_type": "amazon-ebs",
      "build_time": 1754040820,
      "files": null,
      "artifact_id": "ap-south-1:ami-06a090f2b036101f2",
      "packer_run_uuid": "58bc3c8b-e4d9-baad-1b12-ef94b562af8a",
      "custom_data": null
    },
    {
      "name": "rhel10",
      "builder_type": "amazon-ebs",
      "build_time": 1754668905,
      "files": null,
      "artifact_id": "ap-south-1:ami-040a6b2dfcf5cecb6",
      "packer_run_uuid": "98543739-eee7-3040-2a69-f0d239485af9",
      "custom_data": null
    }
  ],
  "last_run_uuid": "98543739-eee7-3040-2a69-f0d239485af9"
}